datarobot/__init__.py
datarobot/_compat.py
datarobot/_version.py
datarobot/analytics.py
datarobot/client.py
datarobot/config.py
datarobot/context.py
datarobot/enums.py
datarobot/errors.py
datarobot/py.typed
datarobot/rest.py
datarobot/_experimental/__init__.py
datarobot/_experimental/fs/__init__.py
datarobot/_experimental/fs/file_system.py
datarobot/_experimental/insights/__init__.py
datarobot/_experimental/insights/confusion_matrix.py
datarobot/_experimental/models/__init__.py
datarobot/_experimental/models/chunking_service.py
datarobot/_experimental/models/data_matching.py
datarobot/_experimental/models/data_store.py
datarobot/_experimental/models/enums.py
datarobot/_experimental/models/files_experimental.py
datarobot/_experimental/models/idiomatic_project.py
datarobot/_experimental/models/model_lineage.py
datarobot/_experimental/models/project_options.py
datarobot/_experimental/models/retraining.py
datarobot/_experimental/models/time_series_transformation_plan.py
datarobot/_experimental/models/time_series_wrangling_template.py
datarobot/_experimental/models/moderation/__init__.py
datarobot/auth/__init__.py
datarobot/auth/exceptions.py
datarobot/auth/identity.py
datarobot/auth/oauth.py
datarobot/auth/session.py
datarobot/auth/typing.py
datarobot/auth/users.py
datarobot/auth/utils.py
datarobot/auth/authlib/__init__.py
datarobot/auth/authlib/oauth.py
datarobot/auth/datarobot/__init__.py
datarobot/auth/datarobot/exceptions.py
datarobot/auth/datarobot/oauth.py
datarobot/core/__init__.py
datarobot/core/config.py
datarobot/core/dev.py
datarobot/helpers/__init__.py
datarobot/helpers/binary_data_utils.py
datarobot/helpers/eligibility_result.py
datarobot/helpers/feature_discovery.py
datarobot/helpers/image_utils.py
datarobot/helpers/partitioning_methods.py
datarobot/insights/__init__.py
datarobot/insights/base.py
datarobot/insights/lift_chart.py
datarobot/insights/residuals.py
datarobot/insights/roc_curve.py
datarobot/insights/shap_distributions.py
datarobot_early_access-3.12.0.2026.1.19.173726.dist-info/licenses/LICENSE.txt
datarobot_early_access-3.12.0.2026.1.19.173726.dist-info/METADATA
datarobot_early_access-3.12.0.2026.1.19.173726.dist-info/WHEEL
datarobot_early_access-3.12.0.2026.1.19.173726.dist-info/entry_points.txt
datarobot_early_access-3.12.0.2026.1.19.173726.dist-info/top_level.txt
datarobot_early_access-3.12.0.2026.1.19.173726.dist-info/RECORD
